mp3stego/__init__.py
mp3stego/steganography.py
mp3stego/utils.py
mp3stego/decoder/Frame.py
mp3stego/decoder/FrameHeader.py
mp3stego/decoder/FrameSideInformation.py
mp3stego/decoder/ID3_Parser.py
mp3stego/decoder/MP3_Parser.py
mp3stego/decoder/__init__.py
mp3stego/decoder/decoder.py
mp3stego/decoder/tables.py
mp3stego/decoder/util.py
mp3stego/encoder/MP3_Encoder.py
mp3stego/encoder/WAV_Reader.py
mp3stego/encoder/__init__.py
mp3stego/encoder/encoder.py
mp3stego/encoder/tables.py
mp3stego/encoder/util.py
mp3stego_lib-1.1.8.dist-info/licenses/LICENSE
tests/__init__.py
tests/steganography_test.py
mp3stego_lib-1.1.8.dist-info/METADATA
mp3stego_lib-1.1.8.dist-info/WHEEL
mp3stego_lib-1.1.8.dist-info/top_level.txt
mp3stego_lib-1.1.8.dist-info/RECORD
