Metadata-Version: 2.4
Name: mp3stego-lib
Version: 1.1.8
Summary: mp3 steganography library
Home-page: https://github.com/tomershay100/mp3-steganography-lib
Author: Aviad Seady, Tomer Shay, Lee Zaid
Author-email: aviadevelops@gmail.com, tomershay100@gmail.com, lizizaid@gmail.com
License: MIT
Project-URL: Bug Tracker, https://github.com/tomershay100/mp3-steganography-lib/issues
Classifier: Intended Audience :: Developers
Classifier: Programming Language :: Python :: 3.9
Classifier: License :: OSI Approved :: MIT License
Classifier: Operating System :: OS Independent
Requires-Python: >=3.9
License-File: LICENSE
Dynamic: author
Dynamic: author-email
Dynamic: classifier
Dynamic: description
Dynamic: description-content-type
Dynamic: home-page
Dynamic: license
Dynamic: license-file
Dynamic: project-url
Dynamic: requires-python
Dynamic: summary
